amiyahttp/__init__.py
amiyahttp/exception.py
amiyahttp/serverBase.py
amiyahttp/auth/__init__.py
amiyahttp/auth/authKey.py
amiyahttp/auth/oauth2.py
amiyahttp-0.0.7.dist-info/LICENSE
amiyahttp-0.0.7.dist-info/METADATA
amiyahttp-0.0.7.dist-info/WHEEL
amiyahttp-0.0.7.dist-info/top_level.txt
amiyahttp-0.0.7.dist-info/RECORD
