Metadata-Version: 2.1
Name: amiyahttp
Version: 0.0.7
Summary: 对 FastApi 进行二次封装的简易 HTTP Web 服务 SDK
Home-page: https://www.amiyabot.com/develop/advanced/httpSupport.html
Author: vivien8261
Author-email: 826197021@qq.com
License: MIT Licence
Requires-Python: >=3.10
License-File: LICENSE
Requires-Dist: amiyalog~=0.0.2
Requires-Dist: amiyautils~=0.0.2
Requires-Dist: bcrypt~=4.3.0
Requires-Dist: fastapi-utils~=0.8.0
Requires-Dist: fastapi~=0.115.14
Requires-Dist: passlib~=1.7.4
Requires-Dist: python-jose[cryptography]~=3.5.0
Requires-Dist: python-multipart~=0.0.20
Requires-Dist: typing-inspect~=0.9.0
Requires-Dist: uvicorn[standard]~=0.35.0
